setup.py
ormdb/Config.py
ormdb/DbStyle.py
ormdb/Elasticsearch.py
ormdb/Field.py
ormdb/LICENSE
ormdb/Log.py
ormdb/LogLevel.py
ormdb/Model.py
ormdb/ModelMetaclass.py
ormdb/MySQL.py
ormdb/README.MD
ormdb/Redis.py
ormdb/Test.py
ormdb/User.py
ormdb/__init__.py
ormdb.egg-info/PKG-INFO
ormdb.egg-info/SOURCES.txt
ormdb.egg-info/dependency_links.txt
ormdb.egg-info/requires.txt
ormdb.egg-info/top_level.txt